telegramstats/__init__.py
telegramstats/__main__.py
telegramstats/parse.py
telegramstats-2.0.1.dist-info/METADATA
telegramstats-2.0.1.dist-info/WHEEL
telegramstats-2.0.1.dist-info/entry_points.txt
telegramstats-2.0.1.dist-info/licenses/LICENSE.txt
telegramstats-2.0.1.dist-info/RECORD
